importer/D3scenario_visualize.py
importer/__init__.py
importer/break_direct_cycles.py
importer/compare_scenarios.py
importer/file_metadata.py
importer/generate_graph.py
importer/generate_landed_cost.py
importer/icons/default.png
importer/icons/distribution.png
importer/icons/operation.png
importer/icons/product.png
importer/icons/resource.png
importer/lsco_network_from_reports.py
importer/lsco_planning.py
importer/test.py
supply/__init__.py
supply/supply.abi3.so
supply_chain_graph-0.1.20.dist-info/METADATA
supply_chain_graph-0.1.20.dist-info/WHEEL
web_python/CLIENT_README.md
web_python/example_client_usage.py
web_python/network_api.py
web_python/requirements.txt
web_python/requirements_client.txt
web_python/run_server.py
web_python/supply_chain_client.py
web_python/test_multiple_sku.py
supply_chain_graph-0.1.20.dist-info/RECORD
