Metadata-Version: 2.4
Name: supply-chain-graph
Version: 0.1.20
Requires-Dist: polars==1.11.0
Requires-Dist: orjson==3.11.2
Requires-Python: >=3.10
